.gitignore
LICENSE.txt
README.md
setup.cfg
setup.py
topsis/__init__.py
topsis/topsis.py
topsis_kanuj_102017188.egg-info/PKG-INFO
topsis_kanuj_102017188.egg-info/SOURCES.txt
topsis_kanuj_102017188.egg-info/dependency_links.txt
topsis_kanuj_102017188.egg-info/entry_points.txt
topsis_kanuj_102017188.egg-info/requires.txt
topsis_kanuj_102017188.egg-info/top_level.txt