Metadata-Version: 2.1
Name: topsis-kanuj-102017188
Version: 1.2
Summary: Python Package implementing TOPSIS method for multi-criteria decision making method
Home-page: https://github.com/kanuj-boora/topsis-17188
Author: Kanuj Boora
Author-email: boorakanuj@gmail.com
License: MIT
Keywords: topsis,mcdm,mcda,TIET,thapar
Platform: UNKNOWN
Classifier: Development Status :: 3 - Alpha
Classifier: Intended Audience :: Developers
Classifier: Topic :: Software Development :: Build Tools
Classifier: License :: OSI Approved :: MIT License
Classifier: Programming Language :: Python :: 3
Classifier: Programming Language :: Python :: 3.4
Classifier: Programming Language :: Python :: 3.5
Classifier: Programming Language :: Python :: 3.6
License-File: LICENSE.txt
